mitosheet_helper_enterprise/__init__.py
mitosheet_helper_enterprise-0.0.3.dist-info/LICENSE
mitosheet_helper_enterprise-0.0.3.dist-info/METADATA
mitosheet_helper_enterprise-0.0.3.dist-info/WHEEL
mitosheet_helper_enterprise-0.0.3.dist-info/top_level.txt
mitosheet_helper_enterprise-0.0.3.dist-info/RECORD
