Metadata-Version: 2.1
Name: mitosheet-helper-enterprise
Version: 0.0.3
Summary: A helper package for mitosheet.
Author-email: Nate Rush <naterush1997@gmail.com>
License: The Mito Enterprise license (the “Enterprise License”)
Project-URL: Homepage, https://github.com/mito-ds/monorepo
Project-URL: Bug Tracker, https://github.com/mito-ds/monorepo/issues
Classifier: Programming Language :: Python :: 3
Classifier: Operating System :: OS Independent
Requires-Python: >=3.6
License-File: LICENSE
